{
  "metadata": {
    "chapter": "ch05",
    "chapter_title": "ClaimCenter Introduction",
    "lesson": "lesson-02",
    "slide_count": 37,
    "slides_with_text": 34,
    "total_words": 1415,
    "avg_confidence": 87.14,
    "processing_time_seconds": 15.5,
    "extracted_at": "2026-02-13T12:08:52.933401"
  },
  "full_text": "Claim Maintenance\n\nLesson\nobjectives\n\n¢ Describe the major parts of a claim\n\nUse the full search capability of ClaimCenter\nDescribe the information available on the\nClaim Summary\n\nNavigate to Claim details from the Claim\nSummary\n\nDescribe what a supervisor does\n\nIn our insurance business, there are a\nlot of parts to a claim. In the old days\nwe used to keep a physical file for\neach claim. Now, we keep the same\ninformation, but electronically. | need\nto know where and how to maintain all\nthe parts of a claim.\n\nJun\nClaims\nSupervisor\n\n| Policy and coverages G\n\n¢ Apolicy is a contract between the\n\ncarrier and the insured in which the\ncarrier promises to cover (indemnify)\nthe insured for specific types of losses policy coverage\n\n« Acoverage is a type of loss that is or\ncan be listed on a policy which the\ncarrier will cover\n\n* In the case of Workers’ Compensation, the\ncoverage(s) is (are) determined by\napplicable laws/acts/regulations\n\n| The claim G\n\nA claim is an event in which one or more (potentially) covered losses occurs\n\n* The policy's line of business determines the claim's line of business\n\nworkers’ comp auto policy property policy\n\n=) |*\n\nworkers’ comp claim auto claim property claim\n\n| Contacts\n\nRoles involved\nwith providing\nservices\n\nRoles involved\ne& with the loss\n( ] event\nC) a)\n\npolicy and\ncoverages\n\nGi\n\n¢ Contact information is captured when\nthe claim is first created\n\n¢ Acontact is a person or organization\nwho has a relationship to a claim,\nsuch as:\n\n+ Aclaimant requesting compensation for a\nloss\n\n* The reporter of the claim\n+ Adoctor treating an injury\n\n+ An auto repair shop providing an estimate\n\n| incidents G\n\neo vetages ¢ An incident is the ‘what’ that was\nlost or damaged\n: mn ¢ An incident is a collection of\nclaim * .\ninformation about damage\n\n* It typically represents an item that\nwas lost or damaged, such as:\n\n+ Apperson suffering one or more injuries\n+ Lost wages\n\n| Service Requests\n\npolicy and\ncoverages\n\nclaim | ANI\n\nGi\n\n¢ Aservice request is a request for\nwork to be performed by a vendor,\nusually related to an incident.\n\n+ Examples include hospitalization, emergency\nevacuation, physical therapy, and so on\n\n* Service Request types can include\nQuote only, Service only, or both Quote\nand Service\n\n¢ Service Requests can track quotes\nand vendor communications\n\n| Exposures\n\npolicy and\ncoverages\nclaim mn\n\nG ar aN\n2 Blt\now A} ee\nSF ee\ncontact incident service\n\nea\noe\ne\n\n‘= @\noe\n\n\\ =\n8\nSS\n\nexposure\n\n¢« An exposure is a set of data used to\ntrack a potential indemnity from one\ncoverage to one claimant\n\n« An indemnity is a payment in\ncompensation for a covered loss\n¢ In Workers’ Compensation insurance,\n\nthe goal is to compensate the worker\nfor medical expenses and lost wages\n\n| Activities G\n\npolicy and\ncoverages\n\nAn activity is a task that may\nbe required to process a claim\n\nThe set of activities associated\nwith a given claim is referred\nto as the claim's \"workplan\"\n\nActivity due dates and\nstatuses are used for business\nprocesses and reporting\n\nActivities may be created\n\nLes ON workplan manually or through business\nc—4 Ap .9@ rules\n|| °F oe\n\ncontact incident service exposure\n\n| Documents\n\npolicy and ° A document is an electronic file or ;\n\ncoverages physical piece of paper which contains\ninformation relevant to the claim\n\n* May consist of photographs, diagrams,\nassessments, estimates, and so on\n\n2 BOO & &\n\now NE oo. eer a activity document\nS=2\n\ncontact incident service exposure\n\n| Notes\n\npolicy and\ncoverages\n\nGi\n\nA note is a text entry which details the\nevents, courses of actions, and thought\nprocess of a user during the processing\nof aclaim\n\n@ & [fa b\n\nON activity document note\n\nexposure\n\n| Matters G&G\n\npolicy and A matter is a set of data pertaining to a\ncoverages . . 7\nsingle (potential) lawsuit\n\n| « Matters may include case numbers, court dates,\nclaim primary attorneys, and other details\n\n20@08 OD\now UN EE + P) activity document note matter\nI ;\n\ncontact incident service exposure\n\n| Reserve lines\n\nor (@-\ne;\n\npolicy and\ncoverages\n\nGi\n\nA reserve line is an amount of money set\naside for payments against an exposure\n\nexposure\n\n+ Areserve line is implemented through\ntransactions that add to and subtract from the\n\nreserve line\n\n&, = @\nBSS\nactivity document _ note matter\n\nreserve\n\n| Checks Gi\n\neo vetages Acheck is any type of payment (check,\nelectronic funds transfer)\n| + Acheck may contain multiple payment\nclaim transactions from different reserve lines\n\n2020288 De®\now AN...“ a activity document _ note matter\nS=3\n\ncontact incident service exposure\n\nreserve\n\nTanya\n\nCustomer\n\nService\nRepresentative\n\na\n\nThere are a lot of times when a customer\ncalls in for help, but they don’t know their\nclaim number. They may know anything\nfrom their license number to the amount\nof a check they received. | need to be\nable to find their claim with very little\ninformation.\n\n| Demonstration G\n\nCSR — Claim search and activities\n\nclick here\n\nNote: The demonstration opens a new tab in your browser. When the demonstration ends, the\noriginal course launch window appears. Return to this window to continue this presentation.\n\nAs an adjuster, | have a lot of\nindependent tasks that must be\naddressed every day. These tasks can be\non multiple claims and can have varying\nlevels of importance. | need the ability to\ncheck and organize my workload.\n\n_Tanvi :\nAdjuster \\ee/\n\n| Demonstration G\n\n_. Adjuster — Check workplan and\n— documents\nclick here\n\nNote: The demonstration opens a new tab in your browser. When the demonstration ends, the\noriginal course launch window appears. Return to this window to continue this presentation.\n\nAs a supervisor, | am responsible for\nensuring that claims are processed\ncorrectly and in a timely manner. | need\nto know if there are issues that require\nspecial attention. | also need to manage\nmy team’s workload.\n\nJun\nClaims ¢\nSupervisor\n\n| Demonstration G\n\nSupervisor — Check escalated activities\n\nclick here\n\nNote: The demonstration opens a new tab in your browser. When the demonstration ends, the\noriginal course launch window appears. Return to this window to continue this presentation.\n\n| Virtual Machine Instructions G&G\n\nA If you have access to a VM, start the ClaimCenter application in the VM now.\n\n4\n—\nOpen the ClaimCenter _ Before starting Allow the startup Look out for the message\nShortcuts folder on exercises, Start process to run. indicating that the -\nthe Desktop. ClaimCenter application server is ready.\n\nEee nittp://localhost:8080/cc/ClaimCenter.do [igus\n\nConnect to the application URL. After finishing\nexercises, Stop\nClaimCenter\n\n| Student exercise\n\nClaim maintenance activity\n\nLesson\nobjectives ¢ Describe the major parts of a claim\n\nreview ¢ Use the full search capability of ClaimCenter\n¢ Describe the information available on the\nClaim Summary\n* Navigate to Claim details from the Claim\nSummary\n¢ Describe what a supervisor does\n\nQuestion G\n\n_— — Within a claim, what is an incident?\n\n¢\n¢\n¢4\n\n-S e S  e  e H\n\nAnswer\n\n_— — Within a claim, what is an incident?\n\n¢\n¢\n7\n\nAn incident is the “what” that was lost or damaged.\n\n-SS SS e  e e  e H\n\nQuestion G\n\n_— — Whatare the three types of Service Requests?\n\n¢\n¢\n¢4\n\n-S e S  e  e H\n\nAnswer\n\n,— — Whatare the three types of Service Requests?\n\n¢\n¢\n7\n\nQuote only\nQuote and service\n\nService only\n\n-SS SS e  e e  e H\n\nQuestion G\n\n,— — What is an exposure?\n\n¢\n¢\n¢4\n\n-S e S  e  e H\n\nAnswer G\n\na What is an exposure?\n\n¢\n7\n\nAn exposure is used to track a potential indemnity from one coverage to one\nclaimant.\n\n-SS SS e  e e  e H\n\nQuestion G\n\n,— — Whatis a set of activities on a claim called?\n\n¢\n¢\n¢4\n\n-S e S  e  e H\n\nAnswer G\n\n,— — Whatis a set of activities on a claim called?\n4\n\n¢\n7\n\nA Workplan\n\n-SS SS e  e e  e H\n\nQuestion G\n\n,— — InClaimCenter, what two mechanisms are referred to as a check?\n\n¢\n¢\n¢4\n\n-S e S  e  e H\n\nAnswer G\n\n,— — InClaimCenter, what two mechanisms are referred to as a check?\n4\n\n¢\n7\n\nA physical paper check and an electronic funds transfer\n\n-SS SS e  e e  e H",
  "slides": [
    {
      "filename": "slide-01.png",
      "slide_number": 1,
      "text": "Claim Maintenance",
      "word_count": 2,
      "avg_confidence": 95.67,
      "image_size": {
        "width": 1280,
        "height": 557
      }
    },
    {
      "filename": "slide-02.png",
      "slide_number": 2,
      "text": "Lesson\nobjectives\n\n¢ Describe the major parts of a claim\n\nUse the full search capability of ClaimCenter\nDescribe the information available on the\nClaim Summary\n\nNavigate to Claim details from the Claim\nSummary\n\nDescribe what a supervisor does",
      "word_count": 38,
      "avg_confidence": 94.79,
      "image_size": {
        "width": 1280,
        "height": 670
      }
    },
    {
      "filename": "slide-03.png",
      "slide_number": 3,
      "text": "In our insurance business, there are a\nlot of parts to a claim. In the old days\nwe used to keep a physical file for\neach claim. Now, we keep the same\ninformation, but electronically. | need\nto know where and how to maintain all\nthe parts of a claim.\n\nJun\nClaims\nSupervisor",
      "word_count": 53,
      "avg_confidence": 94.93,
      "image_size": {
        "width": 1280,
        "height": 670
      }
    },
    {
      "filename": "slide-04.png",
      "slide_number": 4,
      "text": "| Policy and coverages G\n\n¢ Apolicy is a contract between the\n\ncarrier and the insured in which the\ncarrier promises to cover (indemnify)\nthe insured for specific types of losses policy coverage\n\n« Acoverage is a type of loss that is or\ncan be listed on a policy which the\ncarrier will cover\n\n* In the case of Workers’ Compensation, the\ncoverage(s) is (are) determined by\napplicable laws/acts/regulations",
      "word_count": 69,
      "avg_confidence": 92.8,
      "image_size": {
        "width": 1280,
        "height": 670
      }
    },
    {
      "filename": "slide-05.png",
      "slide_number": 5,
      "text": "| The claim G\n\nA claim is an event in which one or more (potentially) covered losses occurs\n\n* The policy's line of business determines the claim's line of business\n\nworkers’ comp auto policy property policy\n\n=) |*\n\nworkers’ comp claim auto claim property claim",
      "word_count": 45,
      "avg_confidence": 86.12,
      "image_size": {
        "width": 1280,
        "height": 670
      }
    },
    {
      "filename": "slide-06.png",
      "slide_number": 6,
      "text": "| Contacts\n\nRoles involved\nwith providing\nservices\n\nRoles involved\ne& with the loss\n( ] event\nC) a)\n\npolicy and\ncoverages\n\nGi\n\n¢ Contact information is captured when\nthe claim is first created\n\n¢ Acontact is a person or organization\nwho has a relationship to a claim,\nsuch as:\n\n+ Aclaimant requesting compensation for a\nloss\n\n* The reporter of the claim\n+ Adoctor treating an injury\n\n+ An auto repair shop providing an estimate",
      "word_count": 75,
      "avg_confidence": 87.47,
      "image_size": {
        "width": 1280,
        "height": 670
      }
    },
    {
      "filename": "slide-07.png",
      "slide_number": 7,
      "text": "| incidents G\n\neo vetages ¢ An incident is the ‘what’ that was\nlost or damaged\n: mn ¢ An incident is a collection of\nclaim * .\ninformation about damage\n\n* It typically represents an item that\nwas lost or damaged, such as:\n\n+ Apperson suffering one or more injuries\n+ Lost wages",
      "word_count": 54,
      "avg_confidence": 81.27,
      "image_size": {
        "width": 1280,
        "height": 670
      }
    },
    {
      "filename": "slide-08.png",
      "slide_number": 8,
      "text": "| Service Requests\n\npolicy and\ncoverages\n\nclaim | ANI\n\nGi\n\n¢ Aservice request is a request for\nwork to be performed by a vendor,\nusually related to an incident.\n\n+ Examples include hospitalization, emergency\nevacuation, physical therapy, and so on\n\n* Service Request types can include\nQuote only, Service only, or both Quote\nand Service\n\n¢ Service Requests can track quotes\nand vendor communications",
      "word_count": 64,
      "avg_confidence": 89.14,
      "image_size": {
        "width": 1280,
        "height": 670
      }
    },
    {
      "filename": "slide-09.png",
      "slide_number": 9,
      "text": "| Exposures\n\npolicy and\ncoverages\nclaim mn\n\nG ar aN\n2 Blt\now A} ee\nSF ee\ncontact incident service\n\nea\noe\ne\n\n‘= @\noe\n\n\\ =\n8\nSS\n\nexposure\n\n¢« An exposure is a set of data used to\ntrack a potential indemnity from one\ncoverage to one claimant\n\n« An indemnity is a payment in\ncompensation for a covered loss\n¢ In Workers’ Compensation insurance,\n\nthe goal is to compensate the worker\nfor medical expenses and lost wages",
      "word_count": 81,
      "avg_confidence": 77.91,
      "image_size": {
        "width": 1280,
        "height": 670
      }
    },
    {
      "filename": "slide-10.png",
      "slide_number": 10,
      "text": "| Activities G\n\npolicy and\ncoverages\n\nAn activity is a task that may\nbe required to process a claim\n\nThe set of activities associated\nwith a given claim is referred\nto as the claim's \"workplan\"\n\nActivity due dates and\nstatuses are used for business\nprocesses and reporting\n\nActivities may be created\n\nLes ON workplan manually or through business\nc—4 Ap .9@ rules\n|| °F oe\n\ncontact incident service exposure",
      "word_count": 69,
      "avg_confidence": 88.01,
      "image_size": {
        "width": 1280,
        "height": 670
      }
    },
    {
      "filename": "slide-11.png",
      "slide_number": 11,
      "text": "| Documents\n\npolicy and ° A document is an electronic file or ;\n\ncoverages physical piece of paper which contains\ninformation relevant to the claim\n\n* May consist of photographs, diagrams,\nassessments, estimates, and so on\n\n2 BOO & &\n\now NE oo. eer a activity document\nS=2\n\ncontact incident service exposure",
      "word_count": 52,
      "avg_confidence": 83.73,
      "image_size": {
        "width": 1280,
        "height": 670
      }
    },
    {
      "filename": "slide-12.png",
      "slide_number": 12,
      "text": "| Notes\n\npolicy and\ncoverages\n\nGi\n\nA note is a text entry which details the\nevents, courses of actions, and thought\nprocess of a user during the processing\nof aclaim\n\n@ & [fa b\n\nON activity document note\n\nexposure",
      "word_count": 39,
      "avg_confidence": 88.56,
      "image_size": {
        "width": 1280,
        "height": 670
      }
    },
    {
      "filename": "slide-13.png",
      "slide_number": 13,
      "text": "| Matters G&G\n\npolicy and A matter is a set of data pertaining to a\ncoverages . . 7\nsingle (potential) lawsuit\n\n| « Matters may include case numbers, court dates,\nclaim primary attorneys, and other details\n\n20@08 OD\now UN EE + P) activity document note matter\nI ;\n\ncontact incident service exposure",
      "word_count": 54,
      "avg_confidence": 76.04,
      "image_size": {
        "width": 1280,
        "height": 670
      }
    },
    {
      "filename": "slide-14.png",
      "slide_number": 14,
      "text": "| Reserve lines\n\nor (@-\ne;\n\npolicy and\ncoverages\n\nGi\n\nA reserve line is an amount of money set\naside for payments against an exposure\n\nexposure\n\n+ Areserve line is implemented through\ntransactions that add to and subtract from the\n\nreserve line\n\n&, = @\nBSS\nactivity document _ note matter\n\nreserve",
      "word_count": 52,
      "avg_confidence": 83.6,
      "image_size": {
        "width": 1280,
        "height": 670
      }
    },
    {
      "filename": "slide-15.png",
      "slide_number": 15,
      "text": "| Checks Gi\n\neo vetages Acheck is any type of payment (check,\nelectronic funds transfer)\n| + Acheck may contain multiple payment\nclaim transactions from different reserve lines\n\n2020288 De®\now AN...“ a activity document _ note matter\nS=3\n\ncontact incident service exposure\n\nreserve",
      "word_count": 44,
      "avg_confidence": 83.6,
      "image_size": {
        "width": 1280,
        "height": 670
      }
    },
    {
      "filename": "slide-16.png",
      "slide_number": 16,
      "text": "Tanya\n\nCustomer\n\nService\nRepresentative\n\na\n\nThere are a lot of times when a customer\ncalls in for help, but they don’t know their\nclaim number. They may know anything\nfrom their license number to the amount\nof a check they received. | need to be\nable to find their claim with very little\ninformation.",
      "word_count": 54,
      "avg_confidence": 94.7,
      "image_size": {
        "width": 1280,
        "height": 670
      }
    },
    {
      "filename": "slide-17.png",
      "slide_number": 17,
      "text": "| Demonstration G\n\nCSR — Claim search and activities\n\nclick here\n\nNote: The demonstration opens a new tab in your browser. When the demonstration ends, the\noriginal course launch window appears. Return to this window to continue this presentation.",
      "word_count": 39,
      "avg_confidence": 94.95,
      "image_size": {
        "width": 1280,
        "height": 670
      }
    },
    {
      "filename": "slide-18.png",
      "slide_number": 18,
      "text": "",
      "word_count": 0,
      "avg_confidence": 0,
      "image_size": {
        "width": 1280,
        "height": 720
      }
    },
    {
      "filename": "slide-19.png",
      "slide_number": 19,
      "text": "As an adjuster, | have a lot of\nindependent tasks that must be\naddressed every day. These tasks can be\non multiple claims and can have varying\nlevels of importance. | need the ability to\ncheck and organize my workload.\n\n_Tanvi :\nAdjuster \\ee/",
      "word_count": 44,
      "avg_confidence": 94.36,
      "image_size": {
        "width": 1280,
        "height": 670
      }
    },
    {
      "filename": "slide-20.png",
      "slide_number": 20,
      "text": "| Demonstration G\n\n_. Adjuster — Check workplan and\n— documents\nclick here\n\nNote: The demonstration opens a new tab in your browser. When the demonstration ends, the\noriginal course launch window appears. Return to this window to continue this presentation.",
      "word_count": 41,
      "avg_confidence": 92.35,
      "image_size": {
        "width": 1280,
        "height": 670
      }
    },
    {
      "filename": "slide-21.png",
      "slide_number": 21,
      "text": "",
      "word_count": 0,
      "avg_confidence": 0,
      "image_size": {
        "width": 1280,
        "height": 720
      }
    },
    {
      "filename": "slide-22.png",
      "slide_number": 22,
      "text": "As a supervisor, | am responsible for\nensuring that claims are processed\ncorrectly and in a timely manner. | need\nto know if there are issues that require\nspecial attention. | also need to manage\nmy team’s workload.\n\nJun\nClaims ¢\nSupervisor",
      "word_count": 42,
      "avg_confidence": 94.42,
      "image_size": {
        "width": 1280,
        "height": 670
      }
    },
    {
      "filename": "slide-23.png",
      "slide_number": 23,
      "text": "| Demonstration G\n\nSupervisor — Check escalated activities\n\nclick here\n\nNote: The demonstration opens a new tab in your browser. When the demonstration ends, the\noriginal course launch window appears. Return to this window to continue this presentation.",
      "word_count": 38,
      "avg_confidence": 95.03,
      "image_size": {
        "width": 1280,
        "height": 670
      }
    },
    {
      "filename": "slide-24.png",
      "slide_number": 24,
      "text": "",
      "word_count": 0,
      "avg_confidence": 0,
      "image_size": {
        "width": 1280,
        "height": 720
      }
    },
    {
      "filename": "slide-25.png",
      "slide_number": 25,
      "text": "| Virtual Machine Instructions G&G\n\nA If you have access to a VM, start the ClaimCenter application in the VM now.\n\n4\n—\nOpen the ClaimCenter _ Before starting Allow the startup Look out for the message\nShortcuts folder on exercises, Start process to run. indicating that the -\nthe Desktop. ClaimCenter application server is ready.\n\nEee nittp://localhost:8080/cc/ClaimCenter.do [igus\n\nConnect to the application URL. After finishing\nexercises, Stop\nClaimCenter",
      "word_count": 69,
      "avg_confidence": 87.26,
      "image_size": {
        "width": 1280,
        "height": 670
      }
    },
    {
      "filename": "slide-26.png",
      "slide_number": 26,
      "text": "| Student exercise\n\nClaim maintenance activity",
      "word_count": 6,
      "avg_confidence": 95.67,
      "image_size": {
        "width": 1280,
        "height": 670
      }
    },
    {
      "filename": "slide-27.png",
      "slide_number": 27,
      "text": "Lesson\nobjectives ¢ Describe the major parts of a claim\n\nreview ¢ Use the full search capability of ClaimCenter\n¢ Describe the information available on the\nClaim Summary\n* Navigate to Claim details from the Claim\nSummary\n¢ Describe what a supervisor does",
      "word_count": 43,
      "avg_confidence": 89.05,
      "image_size": {
        "width": 1280,
        "height": 670
      }
    },
    {
      "filename": "slide-28.png",
      "slide_number": 28,
      "text": "Question G\n\n_— — Within a claim, what is an incident?\n\n¢\n¢\n¢4\n\n-S e S  e  e H",
      "word_count": 20,
      "avg_confidence": 83.92,
      "image_size": {
        "width": 1280,
        "height": 670
      }
    },
    {
      "filename": "slide-29.png",
      "slide_number": 29,
      "text": "Answer\n\n_— — Within a claim, what is an incident?\n\n¢\n¢\n7\n\nAn incident is the “what” that was lost or damaged.\n\n-SS SS e  e e  e H",
      "word_count": 30,
      "avg_confidence": 83.67,
      "image_size": {
        "width": 1280,
        "height": 670
      }
    },
    {
      "filename": "slide-30.png",
      "slide_number": 30,
      "text": "Question G\n\n_— — Whatare the three types of Service Requests?\n\n¢\n¢\n¢4\n\n-S e S  e  e H",
      "word_count": 20,
      "avg_confidence": 82.85,
      "image_size": {
        "width": 1280,
        "height": 670
      }
    },
    {
      "filename": "slide-31.png",
      "slide_number": 31,
      "text": "Answer\n\n,— — Whatare the three types of Service Requests?\n\n¢\n¢\n7\n\nQuote only\nQuote and service\n\nService only\n\n-SS SS e  e e  e H",
      "word_count": 27,
      "avg_confidence": 82.19,
      "image_size": {
        "width": 1280,
        "height": 670
      }
    },
    {
      "filename": "slide-32.png",
      "slide_number": 32,
      "text": "Question G\n\n,— — What is an exposure?\n\n¢\n¢\n¢4\n\n-S e S  e  e H",
      "word_count": 17,
      "avg_confidence": 79.6,
      "image_size": {
        "width": 1280,
        "height": 670
      }
    },
    {
      "filename": "slide-33.png",
      "slide_number": 33,
      "text": "Answer G\n\na What is an exposure?\n\n¢\n7\n\nAn exposure is used to track a potential indemnity from one coverage to one\nclaimant.\n\n-SS SS e  e e  e H",
      "word_count": 31,
      "avg_confidence": 83.84,
      "image_size": {
        "width": 1280,
        "height": 670
      }
    },
    {
      "filename": "slide-34.png",
      "slide_number": 34,
      "text": "Question G\n\n,— — Whatis a set of activities on a claim called?\n\n¢\n¢\n¢4\n\n-S e S  e  e H",
      "word_count": 22,
      "avg_confidence": 83.47,
      "image_size": {
        "width": 1280,
        "height": 670
      }
    },
    {
      "filename": "slide-35.png",
      "slide_number": 35,
      "text": "Answer G\n\n,— — Whatis a set of activities on a claim called?\n4\n\n¢\n7\n\nA Workplan\n\n-SS SS e  e e  e H",
      "word_count": 25,
      "avg_confidence": 73.84,
      "image_size": {
        "width": 1280,
        "height": 670
      }
    },
    {
      "filename": "slide-36.png",
      "slide_number": 36,
      "text": "Question G\n\n,— — InClaimCenter, what two mechanisms are referred to as a check?\n\n¢\n¢\n¢4\n\n-S e S  e  e H",
      "word_count": 23,
      "avg_confidence": 85.75,
      "image_size": {
        "width": 1280,
        "height": 670
      }
    },
    {
      "filename": "slide-37.png",
      "slide_number": 37,
      "text": "Answer G\n\n,— — InClaimCenter, what two mechanisms are referred to as a check?\n4\n\n¢\n7\n\nA physical paper check and an electronic funds transfer\n\n-SS SS e  e e  e H",
      "word_count": 33,
      "avg_confidence": 82.11,
      "image_size": {
        "width": 1280,
        "height": 670
      }
    }
  ]
}